setup.py
tfstate/__init__.py
tfstate/cli.py
tfstate/constants.py
tfstate/convenience.py
tfstate/loader.py
tfstate/utils.py
tfstate.egg-info/PKG-INFO
tfstate.egg-info/SOURCES.txt
tfstate.egg-info/dependency_links.txt
tfstate.egg-info/entry_points.txt
tfstate.egg-info/not-zip-safe
tfstate.egg-info/requires.txt
tfstate.egg-info/top_level.txt