Metadata-Version: 1.0
Name: tfstate
Version: 0.3.0
Summary: Turns terraform output into json from the CLI
Home-page: https://github.com/virtru/tfstate
Author: Reuven V. Gonzales
Author-email: reuven@virtru.com
License: MIT
Platform: *nix
